fracwork/__init__.py
fracwork/fraction.py
fracwork-0.0.1.dist-info/METADATA
fracwork-0.0.1.dist-info/WHEEL
fracwork-0.0.1.dist-info/licenses/LICENSE
fracwork-0.0.1.dist-info/RECORD
