Metadata-Version: 2.4
Name: fracwork
Version: 0.0.1
Summary: This library is created to simplify work with fractions.
Author: mikhaaiil
License-File: LICENSE
Classifier: License :: OSI Approved :: MIT License
Classifier: Operating System :: OS Independent
Classifier: Programming Language :: Python :: 3
Requires-Python: >=3.10.0
